setup.py
keix_message_store.egg-info/PKG-INFO
keix_message_store.egg-info/SOURCES.txt
keix_message_store.egg-info/dependency_links.txt
keix_message_store.egg-info/requires.txt
keix_message_store.egg-info/top_level.txt
message_store/__init__.py
message_store/utils.py