Metadata-Version: 1.2
Name: keix-message-store
Version: 1.0.0b5
Summary: A gRPC client library for the Keix Message Store.
Home-page: UNKNOWN
Author: Keix
Author-email: info@keix.com
License: UNKNOWN
Platform: UNKNOWN
Requires-Python: >3.5.2
